zope.app.server-5.0-py3.9-nspkg.pth
zope/app/server/__init__.py
zope/app/server/accesslog.py
zope/app/server/accesslog.xml
zope/app/server/configure.zcml
zope/app/server/ftp.py
zope/app/server/main.py
zope/app/server/mkzopeinstance.py
zope/app/server/schema.xml
zope/app/server/server.py
zope/app/server/servercontrol.py
zope/app/server/servertype.py
zope/app/server/wsgi.py
zope/app/server/zpasswd.py
zope/app/server/tests/__init__.py
zope/app/server/tests/site.zcml
zope/app/server/tests/test_accesslog.py
zope/app/server/tests/test_ftp.py
zope/app/server/tests/test_main.py
zope/app/server/tests/test_mkzopeinstance.py
zope/app/server/tests/test_schema.py
zope/app/server/tests/test_server.py
zope/app/server/tests/test_servercontrol.py
zope/app/server/tests/test_servertype.py
zope/app/server/tests/test_wsgi.py
zope/app/server/tests/test_zpasswd.py
zope/app/server/zopeskel/bin/debugzope.in
zope/app/server/zopeskel/bin/runzope.in
zope/app/server/zopeskel/etc/zope.conf.in
zope.app.server-5.0.dist-info/LICENSE.txt
zope.app.server-5.0.dist-info/METADATA
zope.app.server-5.0.dist-info/WHEEL
zope.app.server-5.0.dist-info/namespace_packages.txt
zope.app.server-5.0.dist-info/top_level.txt
zope.app.server-5.0.dist-info/RECORD
