Metadata-Version: 2.1
Name: zope.app.server
Version: 5.0
Summary: ZServer integration for Zope 3 Applications
Home-page: https://github.com/zopefoundation/zope.app.server
Author: Zope Corporation and Contributors
Author-email: zope-dev@zope.dev
License: ZPL 2.1
Keywords: zope3 zserver server http ftp wsgi
Classifier: Development Status :: 5 - Production/Stable
Classifier: Environment :: Web Environment
Classifier: Intended Audience :: Developers
Classifier: License :: OSI Approved :: Zope Public License
Classifier: Programming Language :: Python
Classifier: Programming Language :: Python :: 3.7
Classifier: Programming Language :: Python :: 3.8
Classifier: Programming Language :: Python :: 3.9
Classifier: Programming Language :: Python :: 3.10
Classifier: Programming Language :: Python :: 3.11
Classifier: Programming Language :: Python :: Implementation :: CPython
Classifier: Programming Language :: Python :: Implementation :: PyPy
Classifier: Natural Language :: English
Classifier: Operating System :: OS Independent
Classifier: Topic :: Internet :: WWW/HTTP
Classifier: Framework :: Zope :: 3
Requires-Python: >=3.7
License-File: LICENSE.txt
Requires-Dist: setuptools
Requires-Dist: zope.app.applicationcontrol
Requires-Dist: zope.app.appsetup (>=3.11)
Requires-Dist: zope.app.publication
Requires-Dist: zope.app.wsgi
Requires-Dist: zope.configuration
Requires-Dist: zope.deprecation
Requires-Dist: zope.event
Requires-Dist: zope.interface
Requires-Dist: zope.publisher
Requires-Dist: zope.server (>=4.0)
Requires-Dist: zope.password (>=3.6)
Requires-Dist: zope.processlifetime
Requires-Dist: zdaemon
Requires-Dist: ZConfig
Provides-Extra: test
Requires-Dist: zope.testrunner ; extra == 'test'
Requires-Dist: zope.app.testing ; extra == 'test'
Requires-Dist: ZODB[test] ; extra == 'test'
